trading_calendars/__init__.py
trading_calendars/_version.py
trading_calendars/always_open.py
trading_calendars/calendar_helpers.py
trading_calendars/calendar_utils.py
trading_calendars/common_holidays.py
trading_calendars/errors.py
trading_calendars/exchange_calendar_asex.py
trading_calendars/exchange_calendar_bvmf.py
trading_calendars/exchange_calendar_cmes.py
trading_calendars/exchange_calendar_iepa.py
trading_calendars/exchange_calendar_xams.py
trading_calendars/exchange_calendar_xasx.py
trading_calendars/exchange_calendar_xbkk.py
trading_calendars/exchange_calendar_xbog.py
trading_calendars/exchange_calendar_xbom.py
trading_calendars/exchange_calendar_xbru.py
trading_calendars/exchange_calendar_xbud.py
trading_calendars/exchange_calendar_xbue.py
trading_calendars/exchange_calendar_xcbf.py
trading_calendars/exchange_calendar_xcse.py
trading_calendars/exchange_calendar_xdub.py
trading_calendars/exchange_calendar_xetr.py
trading_calendars/exchange_calendar_xfra.py
trading_calendars/exchange_calendar_xhel.py
trading_calendars/exchange_calendar_xhkg.py
trading_calendars/exchange_calendar_xice.py
trading_calendars/exchange_calendar_xidx.py
trading_calendars/exchange_calendar_xist.py
trading_calendars/exchange_calendar_xjse.py
trading_calendars/exchange_calendar_xkar.py
trading_calendars/exchange_calendar_xkls.py
trading_calendars/exchange_calendar_xkrx.py
trading_calendars/exchange_calendar_xlim.py
trading_calendars/exchange_calendar_xlis.py
trading_calendars/exchange_calendar_xlon.py
trading_calendars/exchange_calendar_xmad.py
trading_calendars/exchange_calendar_xmex.py
trading_calendars/exchange_calendar_xmil.py
trading_calendars/exchange_calendar_xmos.py
trading_calendars/exchange_calendar_xnys.py
trading_calendars/exchange_calendar_xnze.py
trading_calendars/exchange_calendar_xosl.py
trading_calendars/exchange_calendar_xpar.py
trading_calendars/exchange_calendar_xphs.py
trading_calendars/exchange_calendar_xpra.py
trading_calendars/exchange_calendar_xses.py
trading_calendars_korea-0.0.1.dist-info/LICENSE
trading_calendars_korea-0.0.1.dist-info/METADATA
trading_calendars_korea-0.0.1.dist-info/WHEEL
trading_calendars_korea-0.0.1.dist-info/entry_points.txt
trading_calendars_korea-0.0.1.dist-info/top_level.txt
trading_calendars_korea-0.0.1.dist-info/RECORD
